[
    {
        "title": "iphone 15",
        "category": "Iphone",
        "releaseYear": 2023,
        "price": 849,
        "memory": 128,
        "colors": "blu",
        "sim": "eSIM, Nano-SIM",
        "system": "IOS 17",
        "display": "OLED 60Hz HDR",
        "ram": 6,
        "battery": 3249,
        "camera": "12MP",
        "camera1": "48MP",
        "image": "https://store.storeimages.cdn-apple.com/1/as-images.apple.com/is/refurb-iphone-15-blue-202412?wid=4000&hei=4000&fmt=jpeg&qlt=90&.v=1731694787476",
        "id": 1,
        "createdAt": "2025-09-16T07:38:07.310Z",
        "updatedAt": "2025-09-16T07:38:07.310Z"
    },
    {
        "title": "iphone 15 Pro",
        "category": "Iphone",
        "releaseYear": 2023,
        "price": 1.329,
        "memory": 256,
        "colors": "nero",
        "sim": "eSIM, Nano-SIM",
        "system": "IOS 17",
        "display": "OLED, 120 Hz, HDR10",
        "ram": 8,
        "battery": 3274,
        "camera": "12MP",
        "camera1": "48MP",
        "image": "https://assets.mmsrg.com/isr/166325/c1/-/ASSET_MP_143664985?x=536&y=402&format=jpg&quality=80&sp=yes&strip=yes&trim&ex=536&ey=402&align=center&resizesource&unsharp=1.5x1+0.7+0.02&cox=0&coy=0&cdx=536&cdy=402",
        "id": 2,
        "createdAt": "2025-09-16T07:39:10.430Z",
        "updatedAt": "2025-09-16T07:39:10.430Z"
    },
    {
        "title": "iphone 16",
        "category": "Iphone",
        "releaseYear": 2024,
        "price": 849,
        "memory": 128,
        "colors": "rosa",
        "sim": "eSIM, Nano-SIM",
        "system": "IOS 18",
        "display": "OLED, 60Hz, HDR10+",
        "ram": 8,
        "battery": 3561,
        "camera": "12MP",
        "camera1": "48MP",
        "image": "https://m.media-amazon.com/images/I/61Ml-IP+73L._UF1000,1000_QL80_.jpg",
        "id": 3,
        "createdAt": "2025-09-16T07:39:41.279Z",
        "updatedAt": "2025-09-16T07:39:41.279Z"
    },
    {
        "title": "iphone 16 Pro",
        "category": "Iphone",
        "releaseYear": 2024,
        "price": 1.329,
        "memory": 256,
        "colors": "marrone",
        "sim": "eSIM, Nano-SIM",
        "system": "IOS 18",
        "display": "OLED, 120 Hz, HDR10+",
        "ram": 8,
        "battery": 3582,
        "camera": "12MP",
        "camera1": "48MP",
        "image": "https://vlmstore.it/wp-content/uploads/2024/09/iphone-16-pro-1tb-titanio-sabbia.jpg",
        "id": 4,
        "createdAt": "2025-09-16T07:40:34.785Z",
        "updatedAt": "2025-09-16T07:40:34.785Z"
    },
    {
        "title": "Google Pixel 10",
        "category": "Pixel",
        "releaseYear": 2025,
        "price": 899,
        "memory": 128,
        "colors": "azzurro",
        "sim": "eSIM, Nano-SIM",
        "system": "Android 16",
        "display": "OLED, 120 Hz, HDR",
        "ram": 12,
        "battery": 4970,
        "camera": "12MP",
        "camera1": "50MP",
        "image": "https://immagini.trovaprezzi.it/magazine/2025/08/Pixel-10-1.jpg",
        "id": 5,
        "createdAt": "2025-09-16T07:41:12.727Z",
        "updatedAt": "2025-09-16T07:41:12.727Z"
    },
    {
        "title": "Google Pixel 9",
        "category": "Pixel",
        "releaseYear": 2024,
        "price": 899,
        "memory": 128,
        "colors": "nero",
        "sim": "eSIM, Nano-SIM",
        "system": "Android 14",
        "display": "OLED, 120 Hz, HDR",
        "ram": 12,
        "battery": 4700,
        "camera": "12MP",
        "camera1": "50MP",
        "image": "https://assets.mmsrg.com/isr/166325/c1/-/ASSET_MP_144469191?x=536&y=402&format=jpg&quality=80&sp=yes&strip=yes&trim&ex=536&ey=402&align=center&resizesource&unsharp=1.5x1+0.7+0.02&cox=0&coy=0&cdx=536&cdy=402",
        "id": 6,
        "createdAt": "2025-09-16T07:43:00.006Z",
        "updatedAt": "2025-09-16T07:43:00.006Z"
    },
    {
        "title": "Google Pixel 9 Pro",
        "category": "Pixel",
        "releaseYear": 2024,
        "price": 1.329,
        "memory": 512,
        "colors": "grigio",
        "sim": "eSIM, Nano-SIM",
        "system": "Android 14",
        "display": "OLED, 120 Hz, HDR10+",
        "ram": 16,
        "battery": 4700,
        "camera": "12MP",
        "camera1": "50MP",
        "image": "https://assets.mmsrg.com/isr/166325/c1/-/ASSET_MP_144469031/fee_786_587_png",
        "id": 7,
        "createdAt": "2025-09-16T07:44:56.740Z",
        "updatedAt": "2025-09-16T07:44:56.740Z"
    },
    {
        "title": "Google Pixel 8",
        "category": "Pixel",
        "releaseYear": 2023,
        "price": 729,
        "memory": 128,
        "colors": "grigio",
        "sim": "eSIM, Nano-SIM",
        "system": "Android 14",
        "display": "AMOLED, 120 Hz, HDR10+",
        "ram": 8,
        "battery": 4485,
        "camera": "10MP",
        "camera1": "50MP",
        "image": "https://thumb.pccomponentes.com/w-530-530/articles/1084/10845080/1315-google-pixel-8-5g-8-128gb-verde-liquen-libre.jpg",
        "id": 8,
        "createdAt": "2025-09-16T07:46:07.399Z",
        "updatedAt": "2025-09-16T07:46:07.399Z"
    },
    {
        "title": "Google Pixel 8 Pro",
        "category": "Pixel",
        "releaseYear": 2023,
        "price": 1.299,
        "memory": 512,
        "colors": "nero",
        "sim": "eSIM, Nano-SIM",
        "system": "Android 14",
        "display": "AMOLED, 120 Hz, HDR10+",
        "ram": 12,
        "battery": 4950,
        "camera": "10MP",
        "camera1": "50MP",
        "image": "https://assets.mmsrg.com/isr/166325/c1/-/ASSET_MP_133629031?x=536&y=402&format=jpg&quality=80&sp=yes&strip=yes&trim&ex=536&ey=402&align=center&resizesource&unsharp=1.5x1+0.7+0.02&cox=0&coy=0&cdx=536&cdy=402",
        "id": 9,
        "createdAt": "2025-09-16T07:47:06.188Z",
        "updatedAt": "2025-09-16T07:47:06.188Z"
    },
    {
        "title": "Google Pixel 10 Pro",
        "category": "Pixel",
        "releaseYear": 2025,
        "price": 1.299,
        "memory": 512,
        "colors": "argento",
        "sim": "eSIM, Nano-SIM",
        "system": "Android 16",
        "display": "OLED, 120 Hz, HDR",
        "ram": 16,
        "battery": 4935,
        "camera": "12MP",
        "camera1": "50MP",
        "image": "https://assets.mmsrg.com/isr/166325/c1/-/ASSET_MMS_159495957?x=536&y=402&format=jpg&quality=80&sp=yes&strip=yes&trim&ex=536&ey=402&align=center&resizesource&unsharp=1.5x1+0.7+0.02&cox=0&coy=0&cdx=536&cdy=402",
        "id": 10,
        "createdAt": "2025-09-16T07:51:18.039Z",
        "updatedAt": "2025-09-16T07:51:18.039Z"
    }
]